[{"StopId":166,"Code":"BX41","Name":"Bến xe An Sương","StopType":"Bến xe","Zone":"Quận 12","Ward":null,"AddressNo":"Bến xe An Sương","Street":"Quốc lộ 22","SupportDisability":"","Status":"Đang khai thác","Lng":106.61337280273438,"Lat":10.843737602233887,"Search":"BxAS BxAS Ql22","Routes":"04, 104, 122, 151, 27, 33, 41, 61-3, 62-5, 65, 71, 74, 85"},{"StopId":167,"Code":"Q12 135","Name":"Bitis","StopType":"Nhà chờ","Zone":"Quận 12","Ward":null,"AddressNo":"487","Street":"Trường Chinh","SupportDisability":"","Status":"Đang khai thác","Lng":106.617347,"Lat":10.838891,"Search":"B 487 TC","Routes":"04, 104, 13, 145, 27, 41, 65, 94"},{"StopId":172,"Code":"Q12 136","Name":"Chùa Lạc Quang","StopType":"Nhà chờ","Zone":"Quận 12","Ward":null,"AddressNo":"257","Street":"Trường Chinh","SupportDisability":"","Status":"Đang khai thác","Lng":106.620212,"Lat":10.834497,"Search":"CLQ 257 TC","Routes":"04, 104, 13, 145, 27, 41, 65, 94"},{"StopId":168,"Code":"Q12 137","Name":"Chùa Vĩnh Phước","StopType":"Nhà chờ","Zone":"Quận 12","Ward":null,"AddressNo":"Chùa Vĩnh Phước","Street":"Trường Chinh","SupportDisability":"","Status":"Đang khai thác","Lng":106.621794,"Lat":10.83202,"Search":"CVP CVP TC","Routes":"04, 104, 13, 145, 27, 41, 65, 94"},{"StopId":169,"Code":"Q12 139","Name":"Cầu Tham Lương - Siêu thị Thiên Hòa","StopType":"Nhà chờ","Zone":"Quận 12","Ward":null,"AddressNo":"21 (Kế 2/6B)","Street":"Trường Chinh","SupportDisability":"","Status":"Đang khai thác","Lng":106.62586,"Lat":10.82624,"Search":"CTL-StTH 21(2/6B) TC","Routes":"04, 104, 13, 145, 23, 27, 41, 62, 65, 94"},{"StopId":174,"Code":"QTP 010","Name":"Trạm Dệt Thành Công","StopType":"Nhà chờ","Zone":"Quận Tân Phú","Ward":"Phường Tây Thạnh","AddressNo":"8","Street":"Trường Chinh","SupportDisability":"Có","Status":"Đang khai thác","Lng":106.629825,"Lat":10.822315,"Search":"TDTC 8 TC","Routes":"04, 104, 13, 145, 23, 27, 32, 41, 62, 65, 94"},{"StopId":173,"Code":"QTP 011","Name":"Trạm KCN Tân Bình","StopType":"Nhà chờ","Zone":"Quận Tân Phú","Ward":"Phường Tây Thạnh","AddressNo":"881","Street":"Trường Chinh","SupportDisability":"Có","Status":"Đang khai thác","Lng":106.630615,"Lat":10.819386,"Search":"TKTB 881 TC","Routes":"04, 104, 13, 145, 23, 27, 28, 62, 65, 94"},{"StopId":176,"Code":"QTP 012","Name":"Ngã 3 Chế Lan Viên","StopType":"Nhà chờ","Zone":"Quận Tân Phú","Ward":"Phường Tây Thạnh","AddressNo":"831 (trước showroom o tô)","Street":"Trường Chinh","SupportDisability":"Có","Status":"Đang khai thác","Lng":106.632377,"Lat":10.814455,"Search":"N3CLV 831(sot TC","Routes":"04, 104, 13, 145, 23, 27, 28, 62, 65, 94"},{"StopId":177,"Code":"QTP 014","Name":"Trạm Đài Liệt Sỹ","StopType":"Nhà chờ","Zone":"Quận Tân Phú","Ward":"Phường Tây Thạnh","AddressNo":"1/3","Street":"Trường Chinh","SupportDisability":"","Status":"Đang khai thác","Lng":106.634019,"Lat":10.808689,"Search":"TDLS 1/3 TC","Routes":"04, 104, 13, 145, 16, 23, 27, 28, 48, 62, 63-1, 65, 94"},{"StopId":178,"Code":"QTB 118","Name":"Thượng Uyển","StopType":"Nhà chờ","Zone":"Quận Tân Bình","Ward":null,"AddressNo":"680 (Thượng Uyển)","Street":"Cộng Hòa","SupportDisability":"","Status":"Đang khai thác","Lng":106.636055,"Lat":10.806144,"Search":"TU 680(U CH","Routes":"04, 104, 145, 28, 63-1"},{"StopId":180,"Code":"QTB 119","Name":"Ngã tư Tân Kỳ Tân Quý","StopType":"Trụ dừng","Zone":"Quận Tân Bình","Ward":null,"AddressNo":"401","Street":"Cộng Hòa","SupportDisability":"","Status":"Đang khai thác","Lng":106.637887,"Lat":10.803541,"Search":"NtTKTQ 401 CH","Routes":"04, 104, 145, 28, 63-1"},{"StopId":181,"Code":"QTB 120","Name":"ETown","StopType":"Nhà chờ","Zone":"Quận Tân Bình","Ward":null,"AddressNo":"ETown","Street":"Cộng Hòa","SupportDisability":"","Status":"Đang khai thác","Lng":106.640253,"Lat":10.802371,"Search":"E E CH","Routes":"04, 104, 145, 28, 63-1"},{"StopId":179,"Code":"QTB 121","Name":"Ngã ba Bình Giã","StopType":"Trụ dừng","Zone":"Quận Tân Bình","Ward":null,"AddressNo":"303","Street":"Cộng Hòa","SupportDisability":"","Status":"Đang khai thác","Lng":106.644292,"Lat":10.802055,"Search":"NbBG 303 CH","Routes":"04, 104, 145, 28, 63-1"},{"StopId":183,"Code":"QTB 122","Name":"Công ty Lô Hội","StopType":"Nhà chờ","Zone":"Quận Tân Bình","Ward":null,"AddressNo":"19A (Công ty Lô Hội)","Street":"Cộng Hòa","SupportDisability":"","Status":"Đang khai thác","Lng":106.650413,"Lat":10.801544,"Search":"CtLH 19A(tLH CH","Routes":"04, 104, 109, 145, 28, 63-1"},{"StopId":182,"Code":"QTB 123","Name":"Pico Plaza","StopType":"Nhà chờ","Zone":"Quận Tân Bình","Ward":null,"AddressNo":"20Bis","Street":"Cộng Hòa","SupportDisability":"","Status":"Đang khai thác","Lng":106.653637,"Lat":10.801254,"Search":"PP 20Bis CH","Routes":"04, 104, 109, 145, 28, 63-1"},{"StopId":185,"Code":"QTB 124","Name":"Ngã ba Út tịch","StopType":"Trụ dừng","Zone":"Quận Tân Bình","Ward":null,"AddressNo":"35-37","Street":"Cộng Hòa","SupportDisability":"","Status":"Đang khai thác","Lng":106.656679,"Lat":10.800985,"Search":"NbÚt 35-37 CH","Routes":"04, 104, 109, 145, 28, 63-1"},{"StopId":184,"Code":"QTB 125","Name":"Siêu thị Maximart Cộng Hòa","StopType":"Nhà chờ","Zone":"Quận Tân Bình","Ward":null,"AddressNo":"Đối diện 58 (Siêu thị Maximart)","Street":"Cộng Hòa","SupportDisability":"","Status":"Đang khai thác","Lng":106.658819,"Lat":10.800833,"Search":"StMCH Dd58(tM CH","Routes":"04, 104, 109, 145, 28, 63-1"},{"StopId":187,"Code":"QTB 036","Name":"Công viên Hoàng Văn Thụ","StopType":"Nhà chờ","Zone":"Quận Tân Bình","Ward":null,"AddressNo":"259","Street":"Hoàng Văn Thụ","SupportDisability":"","Status":"Đang khai thác","Lng":106.663578,"Lat":10.800469,"Search":"CvHVT 259 HVT","Routes":"04, 08, 103, 104, 109, 148, 50, 59, 63-1, 64, 72-2B"},{"StopId":186,"Code":"QTB 037","Name":"Bảo Tàng Miền Đông","StopType":"Nhà chờ","Zone":"Quận Tân Bình","Ward":null,"AddressNo":"247","Street":"Hoàng Văn Thụ","SupportDisability":"","Status":"Đang khai thác","Lng":106.666372,"Lat":10.800237,"Search":"BTMD 247 HVT","Routes":"04, 08, 104, 109, 152, 63-1, 64, 72-2B"},{"StopId":188,"Code":"QPN 043","Name":"Cây xăng Quân khu 7","StopType":"Trụ dừng","Zone":"Quận Phú Nhuận","Ward":null,"AddressNo":"307","Street":"Nguyễn Văn Trỗi","SupportDisability":"","Status":"Đang khai thác","Lng":106.66847,"Lat":10.799589,"Search":"CxQk7 307 NVT","Routes":"04, 109, 152, 72-2B"},{"StopId":190,"Code":"QPN 044","Name":"Bệnh viện Quận Phú Nhuận","StopType":"Trụ dừng","Zone":"Quận Phú Nhuận","Ward":null,"AddressNo":"279","Street":"Nguyễn Văn Trỗi","SupportDisability":"","Status":"Đang khai thác","Lng":106.670744,"Lat":10.798282,"Search":"BvQPN 279 NVT","Routes":"04, 109, 152, 72-2B"},{"StopId":191,"Code":"QPN 045","Name":"Cổng Xe lửa","StopType":"Trụ dừng","Zone":"Quận Phú Nhuận","Ward":null,"AddressNo":"253","Street":"Nguyễn Văn Trỗi","SupportDisability":"","Status":"Đang khai thác","Lng":106.673609,"Lat":10.796596,"Search":"CXl 253 NVT","Routes":"04, 109, 152, 72-2B"},{"StopId":189,"Code":"QPN 046","Name":"Trung tâm Văn hóa Quận Phú Nhuận","StopType":"Trụ dừng","Zone":"Quận Phú Nhuận","Ward":null,"AddressNo":"157","Street":"Nguyễn Văn Trỗi","SupportDisability":"","Status":"Đang khai thác","Lng":106.675894,"Lat":10.795236,"Search":"TtVhQPN 157 NVT","Routes":"04, 109, 152, 72-2B"},{"StopId":193,"Code":"QPN 047","Name":"Ngã tư Trần Huy Liệu","StopType":"Trụ dừng","Zone":"Quận Phú Nhuận","Ward":null,"AddressNo":"101","Street":"Nguyễn Văn Trỗi","SupportDisability":"","Status":"Đang khai thác","Lng":106.679167,"Lat":10.793276,"Search":"NtTHL 101 NVT","Routes":"04, 109, 152, 72-2B"},{"StopId":192,"Code":"Q3 052","Name":"Chùa Vĩnh Nghiêm","StopType":"Trụ dừng","Zone":"Quận 3","Ward":"Phường 07","AddressNo":"321-323","Street":"Nam Kỳ Khởi Nghĩa","SupportDisability":"","Status":"Đang khai thác","Lng":106.683022,"Lat":10.790381,"Search":"CVN 321-323 NKKN","Routes":"04, 109, 152, 72-1, 72-2B"},{"StopId":196,"Code":"Q3 053","Name":"Trần Quốc Toản","StopType":"Trụ dừng","Zone":"Quận 3","Ward":"Phường 07","AddressNo":"201 F-E","Street":"Nam Kỳ Khởi Nghĩa","SupportDisability":"","Status":"Đang khai thác","Lng":106.686897,"Lat":10.786831,"Search":"TQT 201F NKKN","Routes":"04, 109, 152, 72-2B"},{"StopId":194,"Code":"Q3 054","Name":"Viện Pasteur","StopType":"Nhà chờ","Zone":"Quận 3","Ward":"Phường 07","AddressNo":"179","Street":"Nam Kỳ Khởi Nghĩa","SupportDisability":"","Status":"Đang khai thác","Lng":106.688474,"Lat":10.785351,"Search":"VP 179 NKKN","Routes":"04, 109, 152, 72-2B"},{"StopId":198,"Code":"Q3 055","Name":"Điện Biên Phủ","StopType":"Nhà chờ","Zone":"Quận 3","Ward":null,"AddressNo":"159","Street":"Nam Kỳ Khởi Nghĩa","SupportDisability":"Có","Status":"Đang khai thác","Lng":106.69099,"Lat":10.783116,"Search":"DBP 159 NKKN","Routes":"04, 109, 152, 72-2B"},{"StopId":195,"Code":"Q3 056","Name":"Coop Mart Nguyễn Đình Chiểu","StopType":"Nhà chờ","Zone":"Quận 3","Ward":null,"AddressNo":"143","Street":"Nam Kỳ Khởi Nghĩa","SupportDisability":"","Status":"Đang khai thác","Lng":106.693152,"Lat":10.78113,"Search":"CMNDC 143 NKKN","Routes":"04, 109, 152, 31, 72-2B, 93"},{"StopId":197,"Code":"Q3 057","Name":"Trường THPT Lê Quý Đôn","StopType":"Nhà chờ","Zone":"Quận 3","Ward":null,"AddressNo":"Đối diện 166 - 168","Street":"Nam Kỳ Khởi Nghĩa","SupportDisability":"","Status":"Đang khai thác","Lng":106.69452,"Lat":10.779844,"Search":"TTLQD Dd166-168 NKKN","Routes":"04, 109, 152, 31, 72-2B, 93"},{"StopId":200,"Code":"Q1 075","Name":"Tòa án Nhân dân Thành Phố","StopType":"Nhà chờ","Zone":"Quận 1","Ward":null,"AddressNo":"131","Street":"Nam Kỳ Khởi Nghĩa","SupportDisability":"","Status":"Đang khai thác","Lng":106.698647,"Lat":10.776052,"Search":"TaNdTP 131 NKKN","Routes":"04, 109, 152, 171, 18, 31, 36, 52, 72-2B, 93"},{"StopId":199,"Code":"Q1 076","Name":"Chùa Ông","StopType":"Trụ dừng","Zone":"Quận 1","Ward":null,"AddressNo":"Đối diện 96A","Street":"Nam Kỳ Khởi Nghĩa","SupportDisability":"","Status":"Đang khai thác","Lng":106.699722,"Lat":10.773957,"Search":"CO Dd96A NKKN","Routes":"04, 109, 152, 156D, 171, 18, 31, 36, 44, 52, 93"},{"StopId":201,"Code":"Q1 077","Name":"Trường CĐKT Cao Thắng","StopType":"Trụ dừng","Zone":"Quận 1","Ward":null,"AddressNo":"Đối diện 86","Street":"Nam Kỳ Khởi Nghĩa","SupportDisability":"","Status":"Đang khai thác","Lng":106.700851,"Lat":10.771416,"Search":"TCCT Dd86 NKKN","Routes":"04, 109, 152, 171, 18, 31, 36, 44, 52, 93"},{"StopId":82,"Code":"Q1 023","Name":"Trạm Trung chuyển trên đường Hàm Nghi","StopType":"Nhà chờ","Zone":"Quận 1","Ward":"Phường Bến Thành","AddressNo":"Hàm Nghi 16 (140)","Street":"Hàm Nghi","SupportDisability":"","Status":"Đang khai thác","Lng":106.699326,"Lat":10.771243,"Search":"TTctdHN HN16( HN","Routes":"04, 18, 20"},{"StopId":7273,"Code":"Q1 187","Name":"Khách sạn New World","StopType":"Nhà chờ","Zone":"Quận 1","Ward":"Phường Bến Thành","AddressNo":"Số 76","Street":"Lê Lai","SupportDisability":"Có","Status":"Đang khai thác","Lng":106.695946,"Lat":10.770964,"Search":"KsNW S76 LL","Routes":"03, 04, 102, 109, 171, 172, 18, 19, 20, 34, 36, 39, 52, 53, 72-2B, 86, 88, 93, D4"},{"StopId":7274,"Code":"Q1 188","Name":"Nguyễn Thị Nghĩa","StopType":"Trụ dừng","Zone":"Quận 1","Ward":"Phường Bến Thành","AddressNo":"94-96","Street":"Lê Lai","SupportDisability":"Có","Status":"Đang khai thác","Lng":106.693495,"Lat":10.769952,"Search":"NTN 94-96 LL","Routes":"03, 04, 102, 109, 13, 140, 156D, 171, 172, 18, 19, 20, 34, 36, 39, 52, 53, 69, 72, 72-2B, 75, 86, 88, 93, D4"},{"StopId":7275,"Code":"Q1 189","Name":"Tôn Thất Tùng","StopType":"Trụ dừng","Zone":"Quận 1","Ward":"Phường Bến Thành","AddressNo":"202-204","Street":"Lê Lai","SupportDisability":"Có","Status":"Đang khai thác","Lng":106.690469,"Lat":10.768761,"Search":"TTT 202-204 LL","Routes":"03, 04, 102, 109, 13, 140, 156D, 171, 172, 18, 19, 20, 34, 36, 39, 52, 53, 69, 72, 72-2B, 75, 86, 88, 93, D4"},{"StopId":35,"Code":"BX 01","Name":"Bến xe buýt Sài Gòn","StopType":"Bến xe","Zone":"Quận 1","Ward":"Phường Phạm Ngũ Lão","AddressNo":"BẾN XE BUÝT SÀI GÒN","Street":"Lê Lai","SupportDisability":"Có","Status":"Đang khai thác","Lng":106.689362,"Lat":10.767676,"Search":"BxbSG BXBSG LL","Routes":"03, 04, 102, 109, 13, 140, 171, 172, 18, 19, 20, 27, 28, 34, 36, 39, 52, 65, 69, 72, 75, 86, 88, 93, D4, DL03, DL04, DL05"}]