[{"StopId":1403,"Code":"BX44","Name":"Bến xe Miền Đông","StopType":"Bến xe","Zone":"Quận Bình Thạnh","Ward":null,"AddressNo":"Bến xe Miền Đông","Street":"Đinh Bộ Lĩnh","SupportDisability":"","Status":"Đang khai thác","Lng":106.711294,"Lat":10.814733,"Search":"BxMD BxMD DBL","Routes":"14, 146, 24, 43, 45, 60-3, 61-8, 64, 67"},{"StopId":1408,"Code":"QBTH 071","Name":"Ngã năm Liệt Sĩ","StopType":"Trụ dừng","Zone":"Quận Bình Thạnh","Ward":null,"AddressNo":"222/4 Ter","Street":"Nguyễn Xí","SupportDisability":"","Status":"Đang khai thác","Lng":106.710624,"Lat":10.81204,"Search":"NnLS 222/4T NX","Routes":"14, 19, 43, 45, 61-8, 64"},{"StopId":1410,"Code":"QBTH 131","Name":"Chợ Phường 25","StopType":"Trụ dừng","Zone":"Quận Bình Thạnh","Ward":null,"AddressNo":"đối diện 134/4A","Street":"Ung Văn Khiêm","SupportDisability":"","Status":"Đang khai thác","Lng":106.714674,"Lat":10.808304,"Search":"CP25 dd134/4A UVK","Routes":"14, 158, 19, 43, 44, 45"},{"StopId":1405,"Code":"QBTH 034","Name":"Trường ĐH Giao thông Vận tải Tp. HCM","StopType":"Trụ dừng","Zone":"Quận Bình Thạnh","Ward":null,"AddressNo":"127-129","Street":"Nguyễn Gia Trí","SupportDisability":"","Status":"Đang khai thác","Lng":106.716047,"Lat":10.806602,"Search":"TDGtVtTH 127-129 NGT","Routes":"14, 158, 19, 43, 45"},{"StopId":1407,"Code":"QBTH 035","Name":"Đại học Ngoại Thương","StopType":"Trụ dừng","Zone":"Quận Bình Thạnh","Ward":null,"AddressNo":"211-213 (8A)","Street":"Nguyễn Gia Trí","SupportDisability":"","Status":"Đang khai thác","Lng":106.715875,"Lat":10.804795,"Search":"DhNT 211-213( NGT","Routes":"14, 158, 19, 43, 45"},{"StopId":421,"Code":"QBTH 054","Name":"Đại học Hutech","StopType":"Nhà chờ","Zone":"Quận Bình Thạnh","Ward":null,"AddressNo":"483","Street":"Điện Biên Phủ","SupportDisability":"","Status":"Đang khai thác","Lng":106.714856,"Lat":10.801228,"Search":"DhH 483 DBP","Routes":"06, 10, 104, 14, 150, 157, 159, 161, 19, 30, 43, 44, 45, 52, 55, 60-3, 67, 72-1"},{"StopId":423,"Code":"QBTH 053","Name":"Cây xăng dầu","StopType":"Trụ dừng","Zone":"Quận Bình Thạnh","Ward":null,"AddressNo":"419","Street":"Điện Biên Phủ","SupportDisability":"","Status":"Đang khai thác","Lng":106.712834,"Lat":10.801697,"Search":"Cxd 419 DBP","Routes":"06, 10, 104, 14, 150, 157, 159, 161, 19, 30, 43, 44, 45, 52, 55, 67"},{"StopId":368,"Code":"QBTH 130","Name":"Trường trung học Gia Định","StopType":"Trụ dừng","Zone":"Quận Bình Thạnh","Ward":null,"AddressNo":"221","Street":"Xô Viết Nghệ Tĩnh","SupportDisability":"","Status":"Đang khai thác","Lng":106.711037,"Lat":10.79981,"Search":"TthGD 221 XVNT","Routes":"05, 06, 14, 19, 44, 52"},{"StopId":367,"Code":"QBTH 129","Name":"Trường Tiểu học Hồng Hà","StopType":"Nhà chờ","Zone":"Quận Bình Thạnh","Ward":null,"AddressNo":"153","Street":"Xô Viết Nghệ Tĩnh","SupportDisability":"","Status":"Đang khai thác","Lng":106.710591,"Lat":10.797328,"Search":"TThHH 153 XVNT","Routes":"05, 06, 14, 19, 44, 52"},{"StopId":369,"Code":"QBTH 128","Name":"Ngã ba Nguyễn Cửu Vân","StopType":"Trụ dừng","Zone":"Quận Bình Thạnh","Ward":null,"AddressNo":"151","Street":"Xô Viết Nghệ Tĩnh","SupportDisability":"","Status":"Đang khai thác","Lng":106.709443,"Lat":10.79511,"Search":"NbNCV 151 XVNT","Routes":"05, 06, 14, 19, 52"},{"StopId":373,"Code":"QBTH 127","Name":"Nhà thờ Thị Nghè","StopType":"Trụ dừng","Zone":"Quận Bình Thạnh","Ward":null,"AddressNo":"79","Street":"Xô Viết Nghệ Tĩnh","SupportDisability":"","Status":"Đang khai thác","Lng":106.708054,"Lat":10.793661,"Search":"NtTN 79 XVNT","Routes":"05, 06, 14, 19, 52"},{"StopId":370,"Code":"Q1 098","Name":"Thảo Cầm Viên","StopType":"Nhà chờ","Zone":"Quận 1","Ward":null,"AddressNo":"2A","Street":"Nguyễn Thị Minh Khai","SupportDisability":"","Status":"Đang khai thác","Lng":106.705259,"Lat":10.790694,"Search":"TCV 2A NTMK","Routes":"05, 06, 14, 19, 52"},{"StopId":374,"Code":"Q1 099","Name":"Đài truyền hình","StopType":"Nhà chờ","Zone":"Quận 1","Ward":null,"AddressNo":"Đối diện 9","Street":"Nguyễn Thị Minh Khai","SupportDisability":"","Status":"Đang khai thác","Lng":106.702011,"Lat":10.787157,"Search":"Dth Dd9 NTMK","Routes":"05, 06, 14, 45, 52"},{"StopId":371,"Code":"Q1 100","Name":"nhà thờ Mạc Ti Nho","StopType":"Nhà chờ","Zone":"Quận 1","Ward":"Phường Đa Kao","AddressNo":"16A","Street":"Nguyễn Thị Minh Khai","SupportDisability":"","Status":"Đang khai thác","Lng":106.701294,"Lat":10.786397,"Search":"ntMTN 16A NTMK","Routes":"05, 06, 14, 45, 52"},{"StopId":372,"Code":"Q1 101","Name":"Phùng Khắc Khoan","StopType":"Trụ dừng","Zone":"Quận 1","Ward":null,"AddressNo":"2 - 4","Street":"Phùng Khắc Khoan","SupportDisability":"","Status":"Đang khai thác","Lng":106.698586,"Lat":10.784048,"Search":"PKK 2-4 PKK","Routes":"05, 06, 14, 52"},{"StopId":378,"Code":"Q3 085","Name":"Hồ Con Rùa","StopType":"Trụ dừng","Zone":"Quận 3","Ward":null,"AddressNo":"24 - 26","Street":"Trần Cao Vân","SupportDisability":"","Status":"Đang khai thác","Lng":106.696411,"Lat":10.783314,"Search":"HCR 24-26 TCV","Routes":"05, 06, 14, 52"},{"StopId":375,"Code":"Q3 105","Name":"Sân Phan Đình Phùng","StopType":"Nhà chờ","Zone":"Quận 3","Ward":null,"AddressNo":"8","Street":"Võ Văn Tần","SupportDisability":"Có","Status":"Đang khai thác","Lng":106.694402,"Lat":10.781172,"Search":"SPDP 8 VVT","Routes":"05, 06, 14"},{"StopId":377,"Code":"Q3 106","Name":"Bảo tàng chứng tích chiến tranh","StopType":"Nhà chờ","Zone":"Quận 3","Ward":null,"AddressNo":"28","Street":"Võ Văn Tần","SupportDisability":"Có","Status":"Đang khai thác","Lng":106.69254,"Lat":10.779143,"Search":"Btctct 28 VVT","Routes":"05, 06, 14, DL01, DL02, DL05"},{"StopId":376,"Code":"Q3 107","Name":"Trần Quốc Thảo","StopType":"Nhà chờ","Zone":"Quận 3","Ward":"Phường 06","AddressNo":"44","Street":"Võ Văn Tần","SupportDisability":"","Status":"Đang khai thác","Lng":106.691365,"Lat":10.777889,"Search":"TQT 44 VVT","Routes":"05, 06, 14"},{"StopId":379,"Code":"Q3 108","Name":"Đại học Mở thành phố HCM","StopType":"Trụ dừng","Zone":"Quận 3","Ward":null,"AddressNo":"62","Street":"Võ Văn Tần","SupportDisability":"","Status":"Đang khai thác","Lng":106.69004,"Lat":10.776418,"Search":"DhMtpH 62 VVT","Routes":"05, 06, 14"},{"StopId":381,"Code":"Q3 005","Name":"Nguyễn Thị Minh Khai","StopType":"Trụ dừng","Zone":"Quận 3","Ward":null,"AddressNo":"17","Street":"Bà Huyện Thanh Quan","SupportDisability":"","Status":"Đang khai thác","Lng":106.690186,"Lat":10.775102,"Search":"NTMK 17 BHTQ","Routes":"05, 06, 14, 156D"},{"StopId":380,"Code":"Q3 069","Name":"Cách Mạng tháng 8","StopType":"Trụ dừng","Zone":"Quận 3","Ward":null,"AddressNo":"284","Street":"Nguyễn Thị Minh Khai","SupportDisability":"","Status":"Đang khai thác","Lng":106.689021,"Lat":10.77342,"Search":"CMt8 284 NTMK","Routes":"05, 06, 14, 38"},{"StopId":383,"Code":"Q3 070","Name":"Tôn Thất Tùng","StopType":"Trụ dừng","Zone":"Quận 3","Ward":null,"AddressNo":"414","Street":"Nguyễn Thị Minh Khai","SupportDisability":"","Status":"Đang khai thác","Lng":106.686634,"Lat":10.77079,"Search":"TTT 414 NTMK","Routes":"05, 06, 14, 38"},{"StopId":382,"Code":"Q3 071","Name":"Bệnh viện Từ Dũ","StopType":"Trụ dừng","Zone":"Quận 3","Ward":null,"AddressNo":"436","Street":"Nguyễn Thị Minh Khai","SupportDisability":"","Status":"Đang khai thác","Lng":106.684883,"Lat":10.768946,"Search":"BvTD 436 NTMK","Routes":"05, 06, 14, 38"},{"StopId":89,"Code":"Q3 072","Name":"Trung ương Hội Chữ thập đỏ TP","StopType":"Nhà chờ","Zone":"Quận 3","Ward":null,"AddressNo":"464 - 466","Street":"Nguyễn Thị Minh Khai","SupportDisability":"","Status":"Đang khai thác","Lng":106.683657,"Lat":10.767723,"Search":"TuHCtdT 464-466 NTMK","Routes":"05, 06, 14, 27, 38, 53"},{"StopId":90,"Code":"Q3 073","Name":"Nhà sách Minh Khai","StopType":"Trụ dừng","Zone":"Quận 3","Ward":null,"AddressNo":"488","Street":"Nguyễn Thị Minh Khai","SupportDisability":"","Status":"Đang khai thác","Lng":106.68238,"Lat":10.766395,"Search":"NsMK 488 NTMK","Routes":"05, 06, 14, 27, 38, 53"},{"StopId":1409,"Code":"Q3 037","Name":"Nhà khách Chính phủ","StopType":"Nhà chờ","Zone":"Quận 3","Ward":null,"AddressNo":"120","Street":"Lý Thái Tổ","SupportDisability":"","Status":"Đang khai thác","Lng":106.680363,"Lat":10.765963,"Search":"NkCp 120 LTT","Routes":"14, 27"},{"StopId":1413,"Code":"Q3 038","Name":"Nguyễn Đình Chiểu","StopType":"Trụ dừng","Zone":"Quận 3","Ward":null,"AddressNo":"170","Street":"Lý Thái Tổ","SupportDisability":"","Status":"Đang khai thác","Lng":106.678099,"Lat":10.76668,"Search":"NDC 170 LTT","Routes":"14, 150, 27, 69"},{"StopId":1416,"Code":"Q3 039","Name":"Hồ Thị Kỷ","StopType":"Biển treo","Zone":"Quận 3","Ward":null,"AddressNo":"306","Street":"Lý Thái Tổ","SupportDisability":"","Status":"Đang khai thác","Lng":106.675664,"Lat":10.767423,"Search":"HTK 306 LTT","Routes":"14, 150, 27, 69"},{"StopId":1411,"Code":"Q10 029","Name":"Chợ Phường 10","StopType":"Trụ dừng","Zone":"Quận 10","Ward":null,"AddressNo":"430","Street":"Lý Thái Tổ","SupportDisability":"","Status":"Đang khai thác","Lng":106.673051,"Lat":10.767865,"Search":"CP10 430 LTT","Routes":"14, 27, 69"},{"StopId":1412,"Code":"Q10 030","Name":"Bện viện Nhi Đồng 1","StopType":"Nhà chờ","Zone":"Quận 10","Ward":null,"AddressNo":"532","Street":"Lý Thái Tổ","SupportDisability":"","Status":"Đang khai thác","Lng":106.669739,"Lat":10.768029,"Search":"BvND1 532 LTT","Routes":"14, 27, 38, 69"},{"StopId":98,"Code":"Q10 008","Name":"Ngã ba Nguyễn Kim","StopType":"Trụ dừng","Zone":"Quận 10","Ward":null,"AddressNo":"626-628","Street":"Đường 3/2","SupportDisability":"","Status":"Đang khai thác","Lng":106.661743,"Lat":10.764972,"Search":"NbNK 626-628 D3/2","Routes":"14, 27"},{"StopId":100,"Code":"Q11 001","Name":"Nhà sách Phương Nam","StopType":"Nhà chờ","Zone":"Quận 11","Ward":null,"AddressNo":"940 (6B)","Street":"Đường 3/2","SupportDisability":"","Status":"Đang khai thác","Lng":106.658409,"Lat":10.763115,"Search":"NsPN 940( D3/2","Routes":"103, 14, 27"},{"StopId":101,"Code":"Q11 002","Name":"Lê Đại Hành","StopType":"Trụ dừng","Zone":"Quận 11","Ward":null,"AddressNo":"972-974(970)","Street":"Đường 3/2","SupportDisability":"","Status":"Đang khai thác","Lng":106.65603,"Lat":10.761842,"Search":"LDH 972-974(970) D3/2","Routes":"103, 14"},{"StopId":103,"Code":"Q11 003","Name":"Tạ Uyên","StopType":"Trụ dừng","Zone":"Quận 11","Ward":null,"AddressNo":"1114A-1116A","Street":"Đường 3/2","SupportDisability":"","Status":"Đang khai thác","Lng":106.653557,"Lat":10.760535,"Search":"TU 1114A-1116A D3/2","Routes":"103, 14"},{"StopId":105,"Code":"Q11 004","Name":"Xóm Đất","StopType":"Nhà chờ","Zone":"Quận 11","Ward":null,"AddressNo":"1196","Street":"Đường 3/2","SupportDisability":"","Status":"Đang khai thác","Lng":106.650156,"Lat":10.758648,"Search":"XD 1196 D3/2","Routes":"14"},{"StopId":104,"Code":"Q11 005","Name":"Hàn Hải Nguyên","StopType":"Trụ dừng","Zone":"Quận 11","Ward":null,"AddressNo":"1274","Street":"Đường 3/2","SupportDisability":"","Status":"Đang khai thác","Lng":106.647838,"Lat":10.757357,"Search":"HHN 1274 D3/2","Routes":"14"},{"StopId":107,"Code":"Q11 006","Name":"Thái Phiên","StopType":"Trụ dừng","Zone":"Quận 11","Ward":null,"AddressNo":"1354","Street":"Đường 3/2","SupportDisability":"","Status":"Đang khai thác","Lng":106.646034,"Lat":10.756348,"Search":"TP 1354 D3/2","Routes":"14"},{"StopId":106,"Code":"Q11 007","Name":"Vòng xoay Cây Gõ","StopType":"Trụ dừng","Zone":"Quận 11","Ward":null,"AddressNo":"1456","Street":"Đường 3/2","SupportDisability":"","Status":"Đang khai thác","Lng":106.643858,"Lat":10.755207,"Search":"VxCG 1456 D3/2","Routes":"14"},{"StopId":625,"Code":"Q11 097","Name":"Chùa Huê Lâm","StopType":"Ô sơn","Zone":"Quận 11","Ward":null,"AddressNo":"690 (138)","Street":"Hồng Bàng","SupportDisability":"","Status":"Đã hủy","Lng":106.641229,"Lat":10.754558,"Search":"CHL 690( HB","Routes":"09, 14, 62-10, 62-6, 62-7"},{"StopId":623,"Code":"Q11 098","Name":"Tân Hóa","StopType":"Trụ dừng","Zone":"Quận 11","Ward":null,"AddressNo":"732","Street":"Hồng Bàng","SupportDisability":"","Status":"Đang khai thác","Lng":106.639572,"Lat":10.754717,"Search":"TH 732 HB","Routes":"09, 139, 14, 16, 62-1, 62-10, 62-2, 62-6, 62-7, 62-8, 63-1, 81, 84"},{"StopId":626,"Code":"Q6 038","Name":"Cầu Ông Buông","StopType":"Biển treo","Zone":"Quận 6","Ward":null,"AddressNo":"832-834","Street":"Hồng Bàng","SupportDisability":"","Status":"Đang khai thác","Lng":106.635574,"Lat":10.754732,"Search":"COB 832-834 HB","Routes":"09, 139, 14, 16, 32, 62-1, 62-10, 62-2, 62-7, 62-8, 63-1, 84"},{"StopId":627,"Code":"Q6 044","Name":"Vòng xoay Phú Lâm","StopType":"Trụ dừng","Zone":"Quận 6","Ward":null,"AddressNo":"528","Street":"Kinh Dương Vương","SupportDisability":"","Status":"Đang khai thác","Lng":106.633365,"Lat":10.753346,"Search":"VxPL 528 KDV","Routes":"09, 139, 14, 32, 62-1, 62-10, 62-2, 62-8, 63-1, 84"},{"StopId":628,"Code":"Q6 045","Name":"Cư Xá Phú Lâm","StopType":"Nhà chờ","Zone":"Quận 6","Ward":null,"AddressNo":"40-42(580)","Street":"Kinh Dương Vương","SupportDisability":"","Status":"Đang khai thác","Lng":106.63089,"Lat":10.751475,"Search":"CXPL 40-42(580) KDV","Routes":"09, 139, 14, 32, 62-1, 62-10, 62-2, 62-8, 63-1, 84"},{"StopId":629,"Code":"Q6 046","Name":"Hồ Bơi Phú Lâm","StopType":"Trụ dừng","Zone":"Quận 6","Ward":null,"AddressNo":"94-96","Street":"Kinh Dương Vương","SupportDisability":"","Status":"Đang khai thác","Lng":106.628435,"Lat":10.749589,"Search":"HBPL 94-96 KDV","Routes":"09, 139, 14, 32, 62-1, 62-10, 62-2, 62-8, 63-1, 84"},{"StopId":1386,"Code":"Q6 047","Name":"Công Viên Phú Lâm","StopType":"Nhà chờ","Zone":"Quận 6","Ward":null,"AddressNo":"Đối diện 907","Street":"Kinh Dương Vương","SupportDisability":"","Status":"Đang khai thác","Lng":106.624525,"Lat":10.746384,"Search":"CVPL Dd907 KDV","Routes":"09, 139, 14, 32, 62-1, 62-10, 62-2, 62-8, 63-1, 84"},{"StopId":117,"Code":"QBT 011","Name":"Vòng xoay Kinh Dương Vương","StopType":"Trụ dừng","Zone":"Quận Bình Tân","Ward":"Phường An Lạc","AddressNo":"212-214","Street":"Kinh Dương Vương","SupportDisability":"","Status":"Đang khai thác","Lng":106.622475,"Lat":10.744746,"Search":"VxKDV 212-214 KDV","Routes":"09, 10, 139, 14, 148, 25, 32, 61, 62-1, 62-10, 62-2, 62-8, 63-1, 84, 91"},{"StopId":116,"Code":"QBT 012","Name":"Bến xe Miền Tây","StopType":"Trụ dừng","Zone":"Quận Bình Tân","Ward":"Phường An Lạc","AddressNo":"358-360","Street":"Kinh Dương Vương","SupportDisability":"","Status":"Đang khai thác","Lng":106.619096,"Lat":10.741973,"Search":"BxMT 358-360 KDV","Routes":"09, 10, 139, 14, 148, 25, 32, 61, 62-10, 62-2, 62-8, 63-1, 84, 91"},{"StopId":725,"Code":"BX 46","Name":"Bến xe Miền Tây","StopType":"Bến xe","Zone":"Quận Bình Tân","Ward":null,"AddressNo":"Bến xe Miền Tây","Street":"Kinh Dương Vương","SupportDisability":"","Status":"Đang khai thác","Lng":106.619438,"Lat":10.739486,"Search":"BxMT BxMT KDV","Routes":"10, 102, 139, 14, 148, 151, 32, 39, 41, 60-1, 91"}]