[{"StopId":8,"Code":"BX14","Name":"Bến xe buýt Chợ Lớn","StopType":"Bến xe","Zone":"Quận 5","Ward":null,"AddressNo":"GA HKXB CHO LON","Street":"Lê Quang Sung","SupportDisability":"","Status":"Đang khai thác","Lng":106.652565,"Lat":10.751253,"Search":"BxbCL GHCL LQS","Routes":"01, 05, 06, 07, 09, 150, 23, 47, 56, 62-1, 62-10, 62-7, 62-8, 81, 94"},{"StopId":1,"Code":"Q6 095","Name":"Chu Văn An","StopType":"Trụ dừng","Zone":"Quận 6","Ward":null,"AddressNo":"27","Street":"Tháp Mười","SupportDisability":"","Status":"Đang khai thác","Lng":106.652554,"Lat":10.750232,"Search":"CVA 27 TM","Routes":"07, 10, 150, 25, 56, 91"},{"StopId":470,"Code":"Q5 024","Name":"Thuận Kiều Plaza","StopType":"Nhà chờ","Zone":"Quận 5","Ward":null,"AddressNo":"399","Street":"Hồng Bàng","SupportDisability":"","Status":"Đang khai thác","Lng":106.656749,"Lat":10.754111,"Search":"TKP 399 HB","Routes":"06, 139, 150, 63-1, 68"},{"StopId":437,"Code":"Q5 025","Name":"Bệnh viện Chợ Rẫy","StopType":"Trụ dừng","Zone":"Quận 5","Ward":null,"AddressNo":"357-359","Street":"Hồng Bàng","SupportDisability":"","Status":"Đang khai thác","Lng":106.659232,"Lat":10.754553,"Search":"BvCR 357-359 HB","Routes":"06, 07, 08, 10, 139, 150, 56, 62, 63-1, 68"},{"StopId":439,"Code":"Q5 026","Name":"Đại học Y Dược","StopType":"Nhà chờ","Zone":"Quận 5","Ward":null,"AddressNo":"217","Street":"Hồng Bàng","SupportDisability":"","Status":"Đang khai thác","Lng":106.663191,"Lat":10.75536,"Search":"DhYD 217 HB","Routes":"06, 07, 10, 139, 150, 56, 68"},{"StopId":440,"Code":"Q5 027","Name":"Bệnh viện Đại học Y Dược","StopType":"Nhà chờ","Zone":"Quận 5","Ward":null,"AddressNo":"215","Street":"Hồng Bàng","SupportDisability":"","Status":"Đang khai thác","Lng":106.664683,"Lat":10.755671,"Search":"BvDhYD 215 HB","Routes":"06, 07, 10, 139, 150, 56, 68"},{"StopId":432,"Code":"Q5 068","Name":"Công viên Văn Lang","StopType":"Trụ dừng","Zone":"Quận 5","Ward":null,"AddressNo":"132A","Street":"Nguyễn Tri Phương","SupportDisability":"","Status":"Đang khai thác","Lng":106.669613,"Lat":10.757151,"Search":"CvVL 132A NTP","Routes":"06, 07, 10, 139, 150, 56, 59, 68"},{"StopId":441,"Code":"Q5 069","Name":"Trường Trần Khai Nguyên","StopType":"Ô sơn","Zone":"Quận 5","Ward":null,"AddressNo":"138G-138F","Street":"Nguyễn Tri Phương","SupportDisability":"","Status":"Đang khai thác","Lng":106.66928,"Lat":10.758706,"Search":"TTKN 138G-138F NTP","Routes":"07, 10, 150, 59"},{"StopId":285,"Code":"Q10 023","Name":"Trường Khiếm thị Nguyễn Đình Chiểu","StopType":"Trụ dừng","Zone":"Quận 10","Ward":null,"AddressNo":"417","Street":"Ngô Gia Tự","SupportDisability":"","Status":"Đang khai thác","Lng":106.669511,"Lat":10.760582,"Search":"TKtNDC 417 NGT","Routes":"05, 150"},{"StopId":286,"Code":"Q10 024","Name":"Hòa Hảo","StopType":"Trụ dừng","Zone":"Quận 10","Ward":null,"AddressNo":"277","Street":"Ngô Gia Tự","SupportDisability":"","Status":"Đang khai thác","Lng":106.671093,"Lat":10.762933,"Search":"HH 277 NGT","Routes":"05, 150"},{"StopId":1907,"Code":"Q10 025","Name":"Đài tưởng niệm","StopType":"Trụ dừng","Zone":"Quận 10","Ward":null,"AddressNo":"105","Street":"Ngô Gia Tự","SupportDisability":"","Status":"Đang khai thác","Lng":106.672826,"Lat":10.765404,"Search":"Dtn 105 NGT","Routes":"150"},{"StopId":1909,"Code":"Q3 020","Name":"Ngã 7 Lý Thái Tổ","StopType":"Trụ dừng","Zone":"Quận 3","Ward":"Phường 01","AddressNo":"647","Street":"Điện Biên Phủ","SupportDisability":"","Status":"Đang khai thác","Lng":106.675224,"Lat":10.768703,"Search":"N7LTT 647 DBP","Routes":"10, 150, 91"},{"StopId":92,"Code":"Q3 021","Name":"Cao Thắng","StopType":"Ô sơn","Zone":"Quận 3","Ward":"Phường 01","AddressNo":"503-507","Street":"Điện Biên Phủ","SupportDisability":"","Status":"Đang khai thác","Lng":106.67738,"Lat":10.771164,"Search":"CT 503-507 DBP","Routes":"10, 150, 91"},{"StopId":1911,"Code":"Q3 022","Name":"Cư Xá Đô Thành","StopType":"Trụ dừng","Zone":"Quận 3","Ward":"Phường 04","AddressNo":"399","Street":"Điện Biên Phủ","SupportDisability":"","Status":"Đang khai thác","Lng":106.67981,"Lat":10.773248,"Search":"CXDT 399 DBP","Routes":"10, 150, 91"},{"StopId":1912,"Code":"Q3 023","Name":"Bệnh viện Bình Dân","StopType":"Nhà chờ","Zone":"Quận 3","Ward":null,"AddressNo":"371","Street":"Điện Biên Phủ","SupportDisability":"Có","Status":"Đang khai thác","Lng":106.68145,"Lat":10.774641,"Search":"BvBD 371 DBP","Routes":"10, 150, 91"},{"StopId":731,"Code":"Q3 024","Name":"Cách Mạng tháng 8","StopType":"Nhà chờ","Zone":"Quận 3","Ward":null,"AddressNo":"303","Street":"Điện Biên Phủ","SupportDisability":"Có","Status":"Đang khai thác","Lng":106.684145,"Lat":10.777009,"Search":"CMt8 303 DBP","Routes":"10, 150, 30, 91"},{"StopId":1913,"Code":"Q3 025","Name":"Bệnh viện Mắt TPHCM","StopType":"Ô sơn","Zone":"Quận 3","Ward":"Phường 07","AddressNo":"291","Street":"Điện Biên Phủ","SupportDisability":"","Status":"Đang khai thác","Lng":106.685471,"Lat":10.778255,"Search":"BvMT 291 DBP","Routes":"10, 150, 30, 91"},{"StopId":1917,"Code":"Q3 026","Name":"Sở Khoa học và Công nghệ","StopType":"Nhà chờ","Zone":"Quận 3","Ward":null,"AddressNo":"273","Street":"Điện Biên Phủ","SupportDisability":"","Status":"Đang khai thác","Lng":106.687621,"Lat":10.780286,"Search":"SKhvCn 273 DBP","Routes":"10, 150, 30, 91"},{"StopId":1914,"Code":"Q3 027","Name":"Trường Marie Curie","StopType":"Nhà chờ","Zone":"Quận 3","Ward":null,"AddressNo":"Đối diện số 206 (247)","Street":"Điện Biên Phủ","SupportDisability":"Có","Status":"Đang khai thác","Lng":106.690369,"Lat":10.782872,"Search":"TMC Dds206( DBP","Routes":"10, 150, 30, 91"},{"StopId":1920,"Code":"Q3 028","Name":"Phạm Ngọc Thạch","StopType":"Trụ dừng","Zone":"Quận 3","Ward":"Phường 06","AddressNo":"209","Street":"Điện Biên Phủ","SupportDisability":"","Status":"Đang khai thác","Lng":106.692375,"Lat":10.784965,"Search":"PNT 209 DBP","Routes":"10, 150, 30, 72-1, 91, 93"},{"StopId":1915,"Code":"Q1 008","Name":"Công Viên Lê Văn Tám","StopType":"Trụ dừng","Zone":"Quận 1","Ward":null,"AddressNo":"179 - 181","Street":"Điện Biên Phủ","SupportDisability":"","Status":"Đang khai thác","Lng":106.694313,"Lat":10.786934,"Search":"CVLVT 179-181 DBP","Routes":"10, 150, 72-1, 91, 93"},{"StopId":1924,"Code":"Q1 009","Name":"Đinh Tiên Hoàng","StopType":"Trụ dừng","Zone":"Quận 1","Ward":null,"AddressNo":"87","Street":"Điện Biên Phủ","SupportDisability":"","Status":"Đang khai thác","Lng":106.696783,"Lat":10.789477,"Search":"DTH 87 DBP","Routes":"10, 150, 72-1, 91, 93"},{"StopId":730,"Code":"QBTH 063","Name":"Cầu Điện Biên Phủ","StopType":"Trụ dừng","Zone":"Quận Bình Thạnh","Ward":null,"AddressNo":"84","Street":"Điện Biên Phủ","SupportDisability":"","Status":"Đang khai thác","Lng":106.702518,"Lat":10.795115,"Search":"CDBP 84 DBP","Routes":"10, 150, 45, 93"},{"StopId":1916,"Code":"QBTH 062","Name":"Trạm Điện Nguyễn Cửu Vân","StopType":"Nhà chờ","Zone":"Quận Bình Thạnh","Ward":null,"AddressNo":"174","Street":"Điện Biên Phủ","SupportDisability":"","Status":"Đang khai thác","Lng":106.704567,"Lat":10.797286,"Search":"TDNCV 174 DBP","Routes":"10, 150, 159, 45, 93"},{"StopId":1918,"Code":"QBTH 061","Name":"Đại học Hồng Bàng","StopType":"Nhà chờ","Zone":"Quận Bình Thạnh","Ward":null,"AddressNo":"328","Street":"Điện Biên Phủ","SupportDisability":"","Status":"Đang khai thác","Lng":106.707528,"Lat":10.799873,"Search":"DhHB 328 DBP","Routes":"10, 150, 159, 45, 93"},{"StopId":1925,"Code":"QBTH 060","Name":"Vòng xoay Hàng Xanh","StopType":"Nhà chờ","Zone":"Quận Bình Thạnh","Ward":null,"AddressNo":"442","Street":"Điện Biên Phủ","SupportDisability":"","Status":"Đang khai thác","Lng":106.710269,"Lat":10.80108,"Search":"VxHX 442 DBP","Routes":"10, 150, 159, 45, 93"},{"StopId":476,"Code":"QBTH 059","Name":"Đại học Hutech","StopType":"Ô sơn","Zone":"Quận Bình Thạnh","Ward":null,"AddressNo":"510-512","Street":"Điện Biên Phủ","SupportDisability":"","Status":"Đang khai thác","Lng":106.714255,"Lat":10.800827,"Search":"DhH 510-512 DBP","Routes":"06, 10, 104, 150, 157, 159, 161, 30, 43, 52, 55, 60-3, 67, 72-1"},{"StopId":473,"Code":"QBTH 058","Name":"Khu Du lịch Văn Thánh","StopType":"Nhà chờ","Zone":"Quận Bình Thạnh","Ward":null,"AddressNo":"600","Street":"Điện Biên Phủ","SupportDisability":"","Status":"Đang khai thác","Lng":106.717404,"Lat":10.799531,"Search":"KDlVT 600 DBP","Routes":"06, 10, 104, 150, 157, 159, 161, 30, 43, 52, 55, 60-3, 67"},{"StopId":475,"Code":"QBTH 057","Name":"Cầu Sài Gòn","StopType":"Trụ dừng","Zone":"Quận Bình Thạnh","Ward":null,"AddressNo":"658","Street":"Điện Biên Phủ","SupportDisability":"","Status":"Đang khai thác","Lng":106.719496,"Lat":10.798525,"Search":"CSG 658 DBP","Routes":"06, 10, 104, 150, 157, 160, 161, 30, 43, 52, 55, 60-3, 67"},{"StopId":477,"Code":"Q2 071","Name":"Cầu Đen","StopType":"Nhà chờ","Zone":"TP. Thủ Đức - KV1","Ward":"Phường An Phú","AddressNo":"794","Street":"Võ Nguyên Giáp","SupportDisability":"","Status":"Đang khai thác","Lng":106.7342,"Lat":10.799978,"Search":"CD 794 VNG","Routes":"06, 10, 150, 154, 52, 53, 56, 60-3, 67, 72-1"},{"StopId":478,"Code":"Q2 072","Name":"Thảo Điền","StopType":"Nhà chờ","Zone":"TP. Thủ Đức - KV1","Ward":null,"AddressNo":"Đối diện ngã 3 Thảo Điền","Street":"Võ Nguyên Giáp","SupportDisability":"","Status":"Đang khai thác","Lng":106.738899,"Lat":10.800838,"Search":"TD Ddn3TD VNG","Routes":"06, 10, 150, 154, 52, 53, 56, 60-3, 67"},{"StopId":480,"Code":"Q2 073","Name":"Metro Quận 2","StopType":"Nhà chờ","Zone":"TP. Thủ Đức - KV1","Ward":null,"AddressNo":"170","Street":"Võ Nguyên Giáp","SupportDisability":"","Status":"Đang khai thác","Lng":106.742383,"Lat":10.801532,"Search":"MQ2 170 VNG","Routes":"06, 10, 150, 154, 52, 53, 56, 60-3, 67"},{"StopId":479,"Code":"Q2 074","Name":"Cát Lái","StopType":"Nhà chờ","Zone":"TP. Thủ Đức - KV1","Ward":null,"AddressNo":"Khu dân cư Estella","Street":"Võ Nguyên Giáp","SupportDisability":"","Status":"Đang khai thác","Lng":106.748089,"Lat":10.802592,"Search":"CL KdcE VNG","Routes":"06, 10, 150, 52, 53, 56, 60-3, 67"},{"StopId":482,"Code":"Q9 210","Name":"Xi măng hà tiên - trạm thu phí","StopType":"Nhà chờ","Zone":"TP. Thủ Đức - KV2","Ward":"Phường Phước Long A","AddressNo":"249B","Street":"Võ Nguyên Giáp","SupportDisability":"","Status":"Đang khai thác","Lng":106.758655,"Lat":10.820865,"Search":"Xmht-ttp 249B VNG","Routes":"06, 10, 150, 52, 53, 56, 60-3, 67, 99"},{"StopId":481,"Code":"Q9 211","Name":"Ngã 4 Tây Hòa (RMK)","StopType":"Nhà chờ","Zone":"TP. Thủ Đức - KV2","Ward":"Phường Phước Long A","AddressNo":"185A","Street":"Võ Nguyên Giáp","SupportDisability":"","Status":"Đang khai thác","Lng":106.760775,"Lat":10.825972,"Search":"N4TH( 185A VNG","Routes":"06, 10, 150, 52, 53, 56, 60-3, 67, 99"},{"StopId":485,"Code":"Q9 212","Name":"Trạm xây dựng","StopType":"Nhà chờ","Zone":"TP. Thủ Đức - KV2","Ward":"Phường Phước Long A","AddressNo":"354A","Street":"Võ Nguyên Giáp","SupportDisability":"","Status":"Đang khai thác","Lng":106.76312,"Lat":10.829955,"Search":"Txd 354A VNG","Routes":"06, 10, 150, 52, 53, 56, 60-3, 67"},{"StopId":483,"Code":"Q9 213","Name":"Khu QLGTDT số 2","StopType":"Nhà chờ","Zone":"TP. Thủ Đức - KV2","Ward":null,"AddressNo":"Khu QLGTĐT số 2","Street":"Võ Nguyên Giáp","SupportDisability":"","Status":"Đang khai thác","Lng":106.76415,"Lat":10.831921,"Search":"KQs2 KQs2 VNG","Routes":"06, 10, 150, 52, 53, 56, 60-3, 67"},{"StopId":1025,"Code":"Q9 214","Name":"Ngã 4 Bình Thái","StopType":"Nhà chờ","Zone":"TP. Thủ Đức - KV2","Ward":"Phường Phước Long B","AddressNo":"Kho 71","Street":"Võ Nguyên Giáp","SupportDisability":"","Status":"Đang khai thác","Lng":106.76666,"Lat":10.836162,"Search":"N4BT K71 VNG","Routes":"10, 150, 52, 53, 60-3, 67"},{"StopId":1030,"Code":"Q9 215","Name":"UBND quận 9","StopType":"Nhà chờ","Zone":"TP. Thủ Đức - KV2","Ward":"Phường Hiệp Phú","AddressNo":"1B","Street":"Võ Nguyên Giáp","SupportDisability":"","Status":"Đang khai thác","Lng":106.769074,"Lat":10.840466,"Search":"Uq9 1B VNG","Routes":"10, 150, 52, 53, 60-3, 67"},{"StopId":1026,"Code":"Q9 216","Name":"Bê tông Hải Âu","StopType":"Trụ dừng","Zone":"TP. Thủ Đức - KV2","Ward":"Phường Hiệp Phú","AddressNo":"Bê tông Hải Âu","Street":"Võ Nguyên Giáp","SupportDisability":"","Status":"Đang khai thác","Lng":106.77079,"Lat":10.843834,"Search":"BtHA BtHA VNG","Routes":"10, 150, 52, 53, 60-3, 67"},{"StopId":8095,"Code":"TPTĐ 225","Name":"Ga metro Thủ Đức","StopType":"Nhà chờ","Zone":"TP. Thủ Đức - KV2","Ward":"Phường Hiệp Phú","AddressNo":"Đối diện ga metro Thủ Đức","Street":"Xa Lộ Hà Nội","SupportDisability":"Có","Status":"Đang khai thác","Lng":106.772063,"Lat":10.845801,"Search":"GmTD DdgmTD XLHN","Routes":"10, 150, 52, 53, 60-3, 67"},{"StopId":1028,"Code":"Q9 217","Name":"Ngã 4 Thủ Đức","StopType":"Trụ dừng","Zone":"TP. Thủ Đức - KV2","Ward":"Phường Hiệp Phú","AddressNo":"716-720","Street":"Võ Nguyên Giáp","SupportDisability":"","Status":"Đang khai thác","Lng":106.772974,"Lat":10.847142,"Search":"N4TD 716-720 VNG","Routes":"10, 150, 52, 60-3, 67"},{"StopId":494,"Code":"Q9 218","Name":"Công an Quận 9","StopType":"Nhà chờ","Zone":"TP. Thủ Đức - KV2","Ward":null,"AddressNo":"Công an Quận 9","Street":"Xa Lộ Hà Nội","SupportDisability":"","Status":"Đang khai thác","Lng":106.775066,"Lat":10.849966,"Search":"CaQ9 CaQ9 XLHN","Routes":"06, 08, 10, 150, 52, 60-3, 67, 76"},{"StopId":498,"Code":"Q9 219","Name":"Chợ chiều","StopType":"Trụ dừng","Zone":"TP. Thủ Đức - KV2","Ward":"Phường Hiệp Phú","AddressNo":"Kế 830 (Chợ Chiều)","Street":"Xa Lộ Hà Nội","SupportDisability":"","Status":"Đang khai thác","Lng":106.780474,"Lat":10.853511,"Search":"Cc K830(C XLHN","Routes":"08, 10, 150, 52, 60-3, 67, 76"},{"StopId":7159,"Code":"Q9 281","Name":"Trạm Hutech - Khu Công nghệ cao","StopType":"Nhà chờ","Zone":"TP. Thủ Đức - KV2","Ward":"Phường Hiệp Phú","AddressNo":"Trước Trung tâm Đào tạo NL CLC Hutech","Street":"Song hành phải Xa Lộ Hà Nội","SupportDisability":"Có","Status":"Đang khai thác","Lng":106.785523,"Lat":10.856191,"Search":"TH-KCnc TTtDtNCH ShpXLHN","Routes":"06, 08, 10, 150, 52, 60-3, 67, 76"},{"StopId":495,"Code":"Q9 220","Name":"Khu Công nghệ cao quận 9","StopType":"Nhà chờ","Zone":"TP. Thủ Đức - KV2","Ward":null,"AddressNo":"Khu công nghệ cao","Street":"Xa Lộ Hà Nội","SupportDisability":"","Status":"Đang khai thác","Lng":106.788869,"Lat":10.858511,"Search":"KCncq9 Kcnc XLHN","Routes":"06, 08, 10, 150, 164D, 52, 60-3, 67, 76"},{"StopId":536,"Code":"Q9 221","Name":"Cầu Vượt Trạm 2","StopType":"Nhà chờ","Zone":"TP. Thủ Đức - KV2","Ward":null,"AddressNo":"Tiệm vàng Kim Lợi","Street":"Quốc lộ 1","SupportDisability":"","Status":"Đang khai thác","Lng":106.797538,"Lat":10.863595,"Search":"CVT2 TvKL Ql1","Routes":"08, 10, 150, 164D, 19, 33, 53, 60-1, 60-2, 60-3, 61-9, 67, 76, 93"},{"StopId":537,"Code":"Q9 223","Name":"Suối Tiên","StopType":"Trụ dừng","Zone":"TP. Thủ Đức - KV2","Ward":"Phường Tân Phú","AddressNo":"Suối Tiên","Street":"Quốc lộ 1","SupportDisability":"","Status":"Đang khai thác","Lng":106.802081,"Lat":10.866113,"Search":"ST ST Ql1","Routes":"08, 10, 150, 19, 33, 53, 60-1, 60-2, 60-3, 60-7, 61-9, 67, 76, 93, 99"},{"StopId":3715,"Code":"Q9 057","Name":"Nghĩa trang liệt sĩ Tp.HCM","StopType":"Nhà chờ","Zone":"TP. Thủ Đức - KV2","Ward":"Phường Tân Phú","AddressNo":"14-18","Street":"D400","SupportDisability":"","Status":"Đang khai thác","Lng":106.809028,"Lat":10.871371,"Search":"NtlsT 14-18 D","Routes":"150, 61-05, 61-77, 61-9, 67, 76, 93"},{"StopId":3716,"Code":"Q9 058","Name":"Ngã ba Lâm Viên 1","StopType":"Trụ dừng","Zone":"TP. Thủ Đức - KV2","Ward":"Phường Tân Phú","AddressNo":"124","Street":"D400","SupportDisability":"","Status":"Đang khai thác","Lng":106.812891,"Lat":10.87037,"Search":"NbLV1 124 D","Routes":"150, 61-05, 61-77, 61-9, 67, 76, 93"},{"StopId":3717,"Code":"Q9 266","Name":"Đường Hoàng Hữu Nam","StopType":"Ô sơn","Zone":"TP. Thủ Đức - KV2","Ward":null,"AddressNo":"kế 474","Street":"Hoàng Hữu Nam","SupportDisability":"","Status":"Đang khai thác","Lng":106.814522,"Lat":10.87185,"Search":"DHHN k474 HHN","Routes":"150, 61-05, 61-77, 61-9, 67, 76, 93"},{"StopId":7695,"Code":"BX 33","Name":"Bến xe Miền Đông mới","StopType":"Bến xe","Zone":"TP. Thủ Đức - KV2","Ward":"Phường Long Bình","AddressNo":"Bến xe Miền Đông mới","Street":"Quốc lộ 1","SupportDisability":"Có","Status":"Đang khai thác","Lng":106.81497,"Lat":10.878606,"Search":"BxMDm BxMDm Ql1","Routes":"150, 56, 60-7, 61-05, 61-77, 61-9, 67, 76, 93"}]